LICENSE
MANIFEST.in
README.rst
setup.py
virtstrap.egg-info/PKG-INFO
virtstrap.egg-info/SOURCES.txt
virtstrap.egg-info/dependency_links.txt
virtstrap.egg-info/entry_points.txt
virtstrap.egg-info/not-zip-safe
virtstrap.egg-info/requires.txt
virtstrap.egg-info/top_level.txt
virtstrap_support/__init__.py
virtstrap_support/virtstrap-core-0.3.16.tar.gz
virtstrap_support/virtstrap-local-0.3.16.tar.gz
virtstrap_system/__init__.py
virtstrap_system/loaders.py
virtstrap_system/runner.py
virtstrap_system/commands/__init__.py
virtstrap_system/commands/commands.py
virtstrap_system/commands/init.py