Metadata-Version: 1.1
Name: virtstrap
Version: 0.3.16
Summary: virtstrap - Making repeatable environments easy!
Home-page: https://github.com/ravenac95/virtstrap
Author: Reuven V. Gonzales
Author-email: reuven@tobetter.us
License: MIT
Platform: *nix
Classifier: License :: OSI Approved :: MIT License
Classifier: Intended Audience :: Developers
Classifier: Programming Language :: Python
Classifier: Operating System :: POSIX
Classifier: Topic :: Software Development :: Build Tools
